sdk.py
corlace_py-0.0.1.dist-info/LICENSE
corlace_py-0.0.1.dist-info/METADATA
corlace_py-0.0.1.dist-info/WHEEL
corlace_py-0.0.1.dist-info/top_level.txt
corlace_py-0.0.1.dist-info/RECORD
